Innopolis/Fall I/Computer Architecture/hw/task_1/minority.v
module minority (a, b, c, y);
	input a, b, c;
	output y;
	
	// y = !a!b + !a!c + !b!c = 
	// = !a(!b + !c) + !b!c =
	// = !(a + bc (b + c))
	
	assign y = !(a | (b & c) & (b | c));
endmodule

Innopolis/Fall I/Computer Architecture/hw/task_1/minority_tb.v
`timescale 1ns/1ps
`default_nettype none

module minority_test;
	logic a, b, c;
	wire y;
	minority dut(.a(a),.b(b),.c(c),.y(y));

	initial
	begin
    		$dumpfile("minority.vcd");
    		$dumpvars;
		#100 $stop;
	end
initial
begin	
	assign a = 0; assign b = 0; assign c = 0; #5
	if(y == 1)$display("OK. ");
	else $error("Wrong. for %b %b %b result is not %b", a, b, c, y);
	#5
	assign a = 0; assign b = 0; assign c = 1; #5
	if(y == 1)$display("OK.");
	else $error("Wrong. for %b %b %b result is not %b", a, b, c, y);
	#5
	assign a = 0; assign b = 1; assign c = 0; #5
	if(y == 1)$display("OK.");
	else $error("Wrong. for %b %b %b result is not %b", a, b, c, y);
	#5
	assign a = 0; assign b = 1; assign c = 1; #5
	if(y == 0)$display("OK.");
	else $error("Wrong. for %b %b %b result is not %b", a, b, c, y);
	#5
	assign a = 1; assign b = 0; assign c = 0; #5
	if(y == 0)$display("OK.");
	else $error("Wrong. for %b %b %b result is not %b", a, b, c, y);
	#5
	assign a = 1; assign b = 0; assign c = 1; #5
	if(y == 0)$display("OK.");
	else $error("Wrong. for %b %b %b result is not %b", a, b, c, y);
	#5
	assign a = 1; assign b = 1; assign c = 0; #5
	if(y == 0)$display("OK.");
	else $error("Wrong. for %b %b %b result is not %b", a, b, c, y);
	#5
	assign a = 1; assign b = 1; assign c = 1; #5
	if(y == 0)$display("OK.");
	else $error("Wrong. for %b %b %b result is not %b", a, b, c, y);
end
 
endmodule

Innopolis/Fall I/Computer Architecture/hw/task_1/minority.vcd
$date
	Tue Sep 27 23:20:52 2016
$end
$version
	Icarus Verilog
$end
$timescale
	1ps
$end
$scope module minority_test $end
$var wire 1 ! y $end
$var reg 1 " a $end
$var reg 1 # b $end
$var reg 1 $ c $end
$scope module dut $end
$var wire 1 " a $end
$var wire 1 # b $end
$var wire 1 $ c $end
$var wire 1 ! y $end
$upscope $end
$upscope $end
$enddefinitions $end
#0
$dumpvars
0$
0#
0"
1!
$end
#10000
1$
#20000
0$
1#
#30000
0!
1$
#40000
0$
0#
1"
#50000
1$
#60000
0$
1#
#70000
1$
