Innopolis/Fall I/Computer Architecture/hw/task_1/segmentdisplay.v
module segmentdisplay (x1, x2, x3, x4, a, b, c, d, e, f, g);
	input x1, x2, x3, x4;
	output a, b, c, d, e, f, g;
	
	// x1 x2 x3 x4 | a b c d e f g			 	a		    b			c		    d			e		    f			g
	// ------------|--------------			-----------------   -----------------   -----------------   -----------------   -----------------   -----------------   -----------------
	// 0  0  0  0  | 1 1 1 1 1 1 0			| + |   | + | + |   | + | + |   | + |   | + | + |   | + |   | + |   | + | + |   | + |   | + | + |   | + | + | + | + |   |   | + |   | + |   
	// 0  0  0  1  | 0 1 1 0 0 0 0			-----------------   -----------------   -----------------   -----------------   -----------------   -----------------   -----------------
	// 0  0  1  0  | 1 1 0 1 1 0 1			|   | + |   | + |   | + |   | + | + |   | + | + | + | + |   |   | + | + |   |   |   |   | + |   |   |   | + |   | + |   |   | + | + | + |   
	// 0  0  1  1  | 1 1 1 1 0 0 1			-----------------   -----------------   -----------------   -----------------   -----------------   -----------------   -----------------
	// 0  1  0  0  | 0 1 1 0 0 1 1			| + | + | + |   |   | + | + |   |   |   | + | + |   | + |   | + |   |   | + |   |   |   | + | + |   |   |   | + | + |   | + |   | + | + |   
	// 0  1  0  1  | 1 0 1 1 0 1 1			-----------------   -----------------   -----------------   -----------------   -----------------   -----------------   -----------------
	// 0  1  1  0  | 1 0 1 1 1 1 1			| + | + | + | + |   | + |   |   | + |   |   | + |   | + |   | + | + | + |   |   | + | + | + | + |   |   | + | + | + |   | + | + | + | + |   
	// 0  1  1  1  | 1 1 1 0 0 0 0			-----------------   -----------------   -----------------   -----------------   -----------------   -----------------   -----------------
	// 1  0  0  0  | 1 1 1 1 1 1 1			
	// 1  0  0  1  | 1 1 1 0 0 1 1			a = x3!x4 + x1x2x3 + !x1x3x4 + !x1x2x4 + !x2!x3!x4 + x1!x3!x4 + x1!x2!x3
	// 1  0  1  0  | 1 1 1 0 1 1 1			b = !x1!x3!x4 + x1!x3x4 + x1!x2!x4 + !x1x3x4 + !x1!x2
	// 1  0  1  1  | 0 0 1 1 1 1 1			c = !x1x3x4 + !x3x4 + !x2!x3 + !x1x2 + x1!x2
	// 1  1  0  0  | 1 0 0 1 1 1 0			d = !x1!x2!x4 + !x2x3x4 + x2x3!x4 + x2!x3x4 + x1x2!x3 + !x2!x3!x4
	// 1  1  0  1  | 0 1 1 1 1 0 1			e = !x2!x4 + x1x2 + x1x3 + x3!x4
	// 1  1  1  0  | 1 0 0 1 1 1 1			f = !x1x2!x3 + x2x3!x4 + x1x3 + !x3!x4 + x1!x2
	// 1  1  1  1  | 1 0 0 0 1 1 1			g = !x1x2!x3 + x1!x2!x3 + x1x4 + x3!x4 + !x1!x2x3
	
	assign a = x3 & !x4 | x1 & x2 & x3 | !x1 & x3 & x4 | !x1 & x2 & x4 | !x2 & !x3 & !x4 | x1 & !x3 & !x4 | x1 & !x2 & !x3;
	assign b = !x1 & !x3 & !x4 | x1 & !x3 & x4 | x1 & !x2 & !x4 | !x1 & x3 & x4 | !x1 & !x2;
	assign c = !x1 & x3 & x4 | !x3 & x4 | !x2 & !x3 | !x1 & x2 | x1 & !x2;
	assign d = !x1 & !x2 & !x4 | !x2 & x3 & x4 | x2 & x3 & !x4 | x2 & !x3 & x4 | x1 & x2 & !x3 | !x2 & !x3 & !x4;
	assign e = !x2 & !x4 | x1 & x2 | x1 & x3 | x3 & !x4;
	assign f = !x1 & x2 & !x3 | x2 & x3 & !x4 | x1 & x3 | !x3 & !x4 | x1 & !x2;
	assign g = !x1 & x2 & !x3 | x1 & !x2 & !x3 | x1 & x4 | x3 & !x4 | !x1 & !x2 & x3;
endmodule

Innopolis/Fall I/Computer Architecture/hw/task_1/segmentdisplay_tb.v
`timescale 1ns/1ps
`default_nettype none

module segmentdisplay_test;
	logic x1, x2, x3, x4;
	wire a, b, c, d, e, f, g;
	segmentdisplay dut(.x1(x1), .x2(x2), .x3(x3), .x4(x4), .a(a), .b(b), .c(c), .d(d), .e(e), .f(f), .g(g));

	initial
	begin
    		$dumpfile("segmentdisplay.vcd");
    		$dumpvars;
		#200 $stop;
	end
initial
begin	
	// 0  0  0  0  | 1 1 1 1 1 1 0
	assign x1 = 0; assign x2 = 0; assign x3 = 0; assign x4 = 0; #5
	if(a == 1 && b == 1 && c == 1 && d == 1 && e == 1 && f == 1 && g == 0) 
		$display("OK. ");
	else 
		$error("Wrong. for %b %b %b %b result is %b %b %b %b %b %b %b", x1, x2, x3, x4, a, b, c, d, e, f, g); #5
	
	// 0  0  0  1  | 0 1 1 0 0 0 0
	assign x1 = 0; assign x2 = 0; assign x3 = 0; assign x4 = 1; #5
	if(a == 0 && b == 1 && c == 1 && d == 0 && e == 0 && f == 0 && g == 0) 
		$display("OK. ");
	else 
		$error("Wrong. for %b %b %b %b result is %b %b %b %b %b %b %b", x1, x2, x3, x4, a, b, c, d, e, f, g); #5
	
	// 0  0  1  0  | 1 1 0 1 1 0 1
	assign x1 = 0; assign x2 = 0; assign x3 = 1; assign x4 = 0; #5
	if(a == 1 && b == 1 && c == 0 && d == 1 && e == 1 && f == 0 && g == 1) 
		$display("OK. ");
	else 
		$error("Wrong. for %b %b %b %b result is %b %b %b %b %b %b %b", x1, x2, x3, x4, a, b, c, d, e, f, g); #5
	
	// 0  0  1  1  | 1 1 1 1 0 0 1
	assign x1 = 0; assign x2 = 0; assign x3 = 1; assign x4 = 1; #5
	if(a == 1 && b == 1 && c == 1 && d == 1 && e == 0 && f == 0 && g == 1) 
		$display("OK. ");
	else 
		$error("Wrong. for %b %b %b %b result is %b %b %b %b %b %b %b", x1, x2, x3, x4, a, b, c, d, e, f, g); #5
	
	// 0  1  0  0  | 0 1 1 0 0 1 1
	assign x1 = 0; assign x2 = 1; assign x3 = 0; assign x4 = 0; #5
	if(a == 0 && b == 1 && c == 1 && d == 0 && e == 0 && f == 1 && g == 1) 
		$display("OK. ");
	else 
		$error("Wrong. for %b %b %b %b result is %b %b %b %b %b %b %b", x1, x2, x3, x4, a, b, c, d, e, f, g); #5
	
	// 0  1  0  1  | 1 0 1 1 0 1 1
	assign x1 = 0; assign x2 = 1; assign x3 = 0; assign x4 = 1; #5
	if(a == 1 && b == 0 && c == 1 && d == 1 && e == 0 && f == 1 && g == 1) 
		$display("OK. ");
	else 
		$error("Wrong. for %b %b %b %b result is %b %b %b %b %b %b %b", x1, x2, x3, x4, a, b, c, d, e, f, g); #5
	
	// 0  1  1  0  | 1 0 1 1 1 1 1  	
	assign x1 = 0; assign x2 = 1; assign x3 = 1; assign x4 = 0; #5
	if(a == 1 && b == 0 && c == 1 && d == 1 && e == 1 && f == 1 && g == 1) 
		$display("OK. ");
	else 
		$error("Wrong. for %b %b %b %b result is %b %b %b %b %b %b %b", x1, x2, x3, x4, a, b, c, d, e, f, g); #5
	
	// 0  1  1  1  | 1 1 1 0 0 0 0
	assign x1 = 0; assign x2 = 1; assign x3 = 1; assign x4 = 1; #5
	if(a == 1 && b == 1 && c == 1 && d == 0 && e == 0 && f == 0 && g == 0) 
		$display("OK. ");
	else 
		$error("Wrong. for %b %b %b %b result is %b %b %b %b %b %b %b", x1, x2, x3, x4, a, b, c, d, e, f, g); #5
	
	// 1  0  0  0  | 1 1 1 1 1 1 1	
	assign x1 = 1; assign x2 = 0; assign x3 = 0; assign x4 = 0; #5
	if(a == 1 && b == 1 && c == 1 && d == 1 && e == 1 && f == 1 && g == 1) 
		$display("OK. ");
	else 
		$error("Wrong. for %b %b %b %b result is %b %b %b %b %b %b %b", x1, x2, x3, x4, a, b, c, d, e, f, g); #5
	
	// 1  0  0  1  | 1 1 1 0 0 1 1
	assign x1 = 1; assign x2 = 0; assign x3 = 0; assign x4 = 1; #5
	if(a == 1 && b == 1 && c == 1 && d == 0 && e == 0 && f == 1 && g == 1) 
		$display("OK. ");
	else 
		$error("Wrong. for %b %b %b %b result is %b %b %b %b %b %b %b", x1, x2, x3, x4, a, b, c, d, e, f, g); #5
	
	// 1  0  1  0  | 1 1 1 0 1 1 1
	assign x1 = 1; assign x2 = 0; assign x3 = 1; assign x4 = 0; #5
	if(a == 1 && b == 1 && c == 1 && d == 0 && e == 1 && f == 1 && g == 1) 
		$display("OK. ");
	else 
		$error("Wrong. for %b %b %b %b result is %b %b %b %b %b %b %b", x1, x2, x3, x4, a, b, c, d, e, f, g); #5
	
	// 1  0  1  1  | 0 0 1 1 1 1 1
	assign x1 = 1; assign x2 = 0; assign x3 = 1; assign x4 = 1; #5
	if(a == 0 && b == 0 && c == 1 && d == 1 && e == 1 && f == 1 && g == 1) 
		$display("OK. ");
	else 
		$error("Wrong. for %b %b %b %b result is %b %b %b %b %b %b %b", x1, x2, x3, x4, a, b, c, d, e, f, g); #5
	
	// 1  1  0  0  | 1 0 0 1 1 1 0
	assign x1 = 1; assign x2 = 1; assign x3 = 0; assign x4 = 0; #5
	if(a == 1 && b == 0 && c == 0 && d == 1 && e == 1 && f == 1 && g == 0) 
		$display("OK. ");
	else 
		$error("Wrong. for %b %b %b %b result is %b %b %b %b %b %b %b", x1, x2, x3, x4, a, b, c, d, e, f, g); #5
	
	// 1  1  0  1  | 0 1 1 1 1 0 1
	assign x1 = 1; assign x2 = 1; assign x3 = 0; assign x4 = 1; #5
	if(a == 0 && b == 1 && c == 1 && d == 1 && e == 1 && f == 0 && g == 1) 
		$display("OK. ");
	else 
		$error("Wrong. for %b %b %b %b result is %b %b %b %b %b %b %b", x1, x2, x3, x4, a, b, c, d, e, f, g); #5
	
	// 1  1  1  0  | 1 0 0 1 1 1 1
	assign x1 = 1; assign x2 = 1; assign x3 = 1; assign x4 = 0; #5
	if(a == 1 && b == 0 && c == 0 && d == 1 && e == 1 && f == 1 && g == 1) 
		$display("OK. ");
	else 
		$error("Wrong. for %b %b %b %b result is %b %b %b %b %b %b %b", x1, x2, x3, x4, a, b, c, d, e, f, g); #5
	
	// 1  1  1  1  | 1 0 0 0 1 1 1
	assign x1 = 1; assign x2 = 1; assign x3 = 1; assign x4 = 1; #5
	if(a == 1 && b == 0 && c == 0 && d == 0 && e == 1 && f == 1 && g == 1) 
		$display("OK. ");
	else 
		$error("Wrong. for %b %b %b %b result is %b %b %b %b %b %b %b", x1, x2, x3, x4, a, b, c, d, e, f, g);
end
 
endmodule

Innopolis/Fall I/Computer Architecture/hw/task_1/segmentdisplay.vcd
$date
	Wed Sep 28 05:20:18 2016
$end
$version
	Icarus Verilog
$end
$timescale
	1ps
$end
$scope module segmentdisplay_test $end
$var wire 1 ! g $end
$var wire 1 " f $end
$var wire 1 # e $end
$var wire 1 $ d $end
$var wire 1 % c $end
$var wire 1 & b $end
$var wire 1 ' a $end
$var reg 1 ( x1 $end
$var reg 1 ) x2 $end
$var reg 1 * x3 $end
$var reg 1 + x4 $end
$scope module dut $end
$var wire 1 ' a $end
$var wire 1 & b $end
$var wire 1 % c $end
$var wire 1 $ d $end
$var wire 1 # e $end
$var wire 1 " f $end
$var wire 1 ! g $end
$var wire 1 ( x1 $end
$var wire 1 ) x2 $end
$var wire 1 * x3 $end
$var wire 1 + x4 $end
$upscope $end
$upscope $end
$enddefinitions $end
#0
$dumpvars
0+
0*
0)
0(
1'
1&
1%
1$
1#
1"
0!
$end
#10000
0$
0'
0#
0"
1+
#20000
1'
1$
0%
1#
1!
0+
1*
#30000
1%
0#
1+
#40000
0'
0$
1&
1"
1!
0+
0*
1)
#50000
1'
0&
1$
1+
#60000
1'
1#
0+
1*
#70000
0$
0"
1&
0!
0#
1+
#80000
1!
1#
1$
1"
0+
0*
0)
1(
#90000
1&
0#
0$
1+
#100000
1#
1'
0+
1*
#110000
0'
1$
0&
1!
1+
#120000
0!
1'
0%
0+
0*
1)
#130000
1&
1%
1!
0'
0"
1+
#140000
1'
0&
0%
1"
0+
1*
#150000
0$
1!
1+
